mypackage_test/__init__.py
mypackage_test/mymodule.py
mypackage_test_t-0.1.0.dist-info/LICENSE
mypackage_test_t-0.1.0.dist-info/METADATA
mypackage_test_t-0.1.0.dist-info/WHEEL
mypackage_test_t-0.1.0.dist-info/top_level.txt
mypackage_test_t-0.1.0.dist-info/RECORD
